suomilog/__init__.py
suomilog/finnish.py
suomilog/patternparser.py
suomilog/stateparser.py
suomilog-0.9.dist-info/LICENSE
suomilog-0.9.dist-info/METADATA
suomilog-0.9.dist-info/WHEEL
suomilog-0.9.dist-info/top_level.txt
suomilog-0.9.dist-info/RECORD
