Metadata-Version: 2.1
Name: suomilog
Version: 0.9
Summary: Collection of natural language parsing utilities
Home-page: http://github.com/fergusq/suomilog
Author: Iikka Hauhio
Author-email: iikka.hauhio@gmail.com
License: GPL
Platform: UNKNOWN
Classifier: Programming Language :: Python :: 3
Requires-Python: >=3
Requires-Dist: voikko
